eventspype/__init__.py
eventspype/event.py
eventspype/pub/__init__.py
eventspype/pub/multipublisher.py
eventspype/pub/publication.py
eventspype/pub/publisher.py
eventspype/sub/__init__.py
eventspype/sub/functional.py
eventspype/sub/multisubscriber.py
eventspype/sub/reporter.py
eventspype/sub/subscriber.py
eventspype/sub/subscription.py
eventspype/sub/tracker.py
eventspype-1.0.2.dist-info/LICENSE
eventspype-1.0.2.dist-info/METADATA
eventspype-1.0.2.dist-info/WHEEL
eventspype-1.0.2.dist-info/RECORD
