Metadata-Version: 2.1
Name: eventspype
Version: 1.0.2
Summary: A Python framework for building event-driven applications with a clean publisher-subscriber pattern implementation.
Author: Gianluca Pagliara
Author-email: pagliara.gianluca@gmail.com
Requires-Python: >=3.13,<4.0
Classifier: Programming Language :: Python :: 3
Classifier: Programming Language :: Python :: 3.13
